.codecov.yml
.coveragerc
.readthedocs.yml
AUTHORS.md
CITATION.cff
LICENSE
MANIFEST.in
README.md
create_package.txt
doc8.ini
setup.cfg
setup.py
docs/Makefile
docs/source/cli.rst
docs/source/conf.py
docs/source/development.rst
docs/source/framework.jpg
docs/source/index.rst
docs/source/introduction.rst
docs/source/logoIME2.png
src/__init__.py
src/PEMT.egg-info/PKG-INFO
src/PEMT.egg-info/SOURCES.txt
src/PEMT.egg-info/dependency_links.txt
src/PEMT.egg-info/entry_points.txt
src/PEMT.egg-info/not-zip-safe
src/PEMT.egg-info/requires.txt
src/PEMT.egg-info/top_level.txt
src/pemt/__init__.py
src/pemt/__main__.py
src/pemt/cli.py
src/pemt/constants.py
src/pemt/utils.py
src/pemt/chemical_extractor/__init__.py
src/pemt/chemical_extractor/experimental_data_extraction.py
src/pemt/patent_extractor/__init__.py
src/pemt/patent_extractor/patent_chemical_harmonizer.py
src/pemt/patent_extractor/patent_enrichment.py
tests/__init__.py
tests/test_input.py
tests/resources/dummy_gene.tsv