Metadata-Version: 2.1
Name: PEMT
Version: 0.0.2
Summary: A tool for extractor patent literature in drug discovery
Home-page: https://github.com/Fraunhofer-ITMP/PEMT
Author: Yojana Gadiya
Author-email: yojana.gadiya@itmp.fraunhofer.de
Maintainer: Yojana Gadiya
Maintainer-email: yojana.gadiya@itmp.fraunhofer.de
License: MIT
Project-URL: Bug Tracker, https://github.com/Fraunhofer-ITMP/PEMT/issues
Project-URL: Source Code, https://github.com/Fraunhofer-ITMP/PEMT
Project-URL: Documentation, https://pemt.readthedocs.io/en/latest/
Keywords: Drug Discovery,Patent literature,Bioinformatics
Classifier: Development Status :: 4 - Beta
Classifier: Environment :: Console
Classifier: Intended Audience :: Developers
Classifier: Intended Audience :: Science/Research
Classifier: License :: OSI Approved :: MIT License
Classifier: Operating System :: MacOS :: MacOS X
Classifier: Operating System :: Microsoft :: Windows
Classifier: Operating System :: POSIX :: Linux
Classifier: Programming Language :: Python
Classifier: Programming Language :: Python :: 3.8
Classifier: Programming Language :: Python :: 3 :: Only
Classifier: Topic :: Scientific/Engineering :: Bio-Informatics
Requires-Python: >=3.8
Provides-Extra: docs
License-File: LICENSE
